dolosse/__init__.py
dolosse/analysis/__init__.py
dolosse/analysis/ParquetAnalysis/__init__.py
dolosse/analysis/ParquetAnalysis/parquet_analyzer.py
dolosse/analysis/PldToParquet/__init__.py
dolosse/analysis/PldToParquet/__main__.py
dolosse/analysis/PldToParquet/pld_to_parquet.py
dolosse/common/__init__.py
dolosse/common/thread_pool.py
dolosse/common/tests/__init__.py
dolosse/common/tests/decode_buffer_tests.py
dolosse/constants/__init__.py
dolosse/constants/data.py
dolosse/data_formats/__init__.py
dolosse/data_formats/ldf/__init__.py
dolosse/data_formats/ldf/constants.py
dolosse/data_formats/ldf/dir.py
dolosse/data_formats/ldf/header.py
dolosse/data_formats/pld/__init__.py
dolosse/data_formats/pld/header.py
dolosse/hardware/__init__.py
dolosse/hardware/xia/__init__.py
dolosse/hardware/xia/pixie16/__init__.py
dolosse/hardware/xia/pixie16/list_mode_data_decoder.py
dolosse/hardware/xia/pixie16/list_mode_data_mask.py
dolosse/hardware/xia/pixie16/tests/__init__.py
dolosse/hardware/xia/pixie16/tests/list_mode_data_decoder_tests.py
dolosse/hardware/xia/pixie16/tests/list_mode_data_mask_tests.py
dolosse/hardware/xia/pixie16/tests/test_data.py
dolosse/hardware/xia/pixie_net/__init__.py
test/__init__.py
test/cli/__init__.py
test/cli/functional/__init__.py
test/cli/functional/test_kafka_control_cli.py
test/cli/unit/__init__.py
test/cli/unit/test_kafka_control_cli.py
test/generic_json_consumer/__init__.py
test/generic_json_consumer/unit/__init__.py
test/generic_json_consumer/unit/test_generic_json_consumer.py
dolosse-0.7.1.dist-info/LICENSE
dolosse-0.7.1.dist-info/METADATA
dolosse-0.7.1.dist-info/WHEEL
dolosse-0.7.1.dist-info/top_level.txt
dolosse-0.7.1.dist-info/RECORD
