Metadata-Version: 2.1
Name: dolosse
Version: 0.7.1
Summary: A Kafka based data acquisition and analysis framework
Home-page: https://github.com/dolosse/dolosse
Author: S. V. Paulauskas and the Dolosse Collaboration
Author-email: stan@projectscience.tech
License: UNKNOWN
Platform: UNKNOWN
Classifier: Development Status :: 1 - Planning
Classifier: Intended Audience :: Science/Research
Classifier: Programming Language :: Python :: 3
Classifier: License :: OSI Approved :: Apache Software License
Classifier: Topic :: Scientific/Engineering :: Physics
Classifier: Operating System :: OS Independent
License-File: LICENSE
